Metadata-Version: 2.1
Name: diamond-env
Version: 1.0.3
Summary: Minecraft Diamond Env
Home-page: http://github.com/danijar/diamond_env
Author: Danijar Hafner
Classifier: Intended Audience :: Science/Research
Classifier: License :: OSI Approved :: MIT License
Classifier: Programming Language :: Python :: 3
Classifier: Topic :: Scientific/Engineering :: Artificial Intelligence
License-File: LICENSE
